sr_data/__init__.py
sr_data/filtered.py
sr_data/pipeline.py
sr_data/steps/__init__.py
sr_data/steps/combination.py
sr_data/steps/embed.py
sr_data/steps/extract.py
sr_data/steps/filter.py
sr_data/steps/final.py
sr_data/steps/gh_mentions.py
sr_data/steps/junit_tests.py
sr_data/steps/lens.py
sr_data/steps/license_filter.py
sr_data/steps/links.py
sr_data/steps/maven.py
sr_data/steps/mcw.py
sr_data/steps/merge.py
sr_data/steps/no_readme.py
sr_data/steps/numerical.py
sr_data/steps/pulls.py
sr_data/steps/scores.py
sr_data/steps/sentiments.py
sr_data/steps/snippets.py
sr_data/steps/swc.py
sr_data/steps/workflows.py
sr_data-0.0.47.dist-info/LICENSE.txt
sr_data-0.0.47.dist-info/METADATA
sr_data-0.0.47.dist-info/WHEEL
sr_data-0.0.47.dist-info/RECORD
